yteva/__init__.py
yteva/search.py
yteva/yteva.py
yteva-2025.4.15.dist-info/licenses/LICENSE
yteva-2025.4.15.dist-info/METADATA
yteva-2025.4.15.dist-info/WHEEL
yteva-2025.4.15.dist-info/top_level.txt
yteva-2025.4.15.dist-info/RECORD
