Metadata-Version: 2.4
Name: yteva
Version: 2025.4.15
Summary: yteva library for downloading audio and videos from YouTube and details about them.
Home-page: https://t.me/yteva_lib
Author: dev eva
Author-email: source205eva@gmail.com
Classifier: Programming Language :: Python :: 3
Classifier: License :: OSI Approved :: MIT License
Classifier: Operating System :: OS Independent
Requires-Python: >=3.8
License-File: LICENSE
Requires-Dist: aiohttp
Requires-Dist: requests
Requires-Dist: httpx==0.25.0
Requires-Dist: beautifulsoup4
Dynamic: author
Dynamic: author-email
Dynamic: classifier
Dynamic: description
Dynamic: description-content-type
Dynamic: home-page
Dynamic: license-file
Dynamic: requires-dist
Dynamic: requires-python
Dynamic: summary
